pop_serial/conf.py
pop_serial/version.py
pop_serial/serial/json_serial.py
pop_serial/serial/msgpack_serial.py
pop_serial/serial/str_serial.py
pop_serial/serial/contracts/init.py
pop_serial-2.0.0.dist-info/LICENSE
pop_serial-2.0.0.dist-info/METADATA
pop_serial-2.0.0.dist-info/WHEEL
pop_serial-2.0.0.dist-info/entry_points.txt
pop_serial-2.0.0.dist-info/top_level.txt
pop_serial-2.0.0.dist-info/RECORD
