Metadata-Version: 2.1
Name: pop-serial
Version: 2.0.0
Summary: An app-merge component for larger projects that provides a standardized interface for serializing and de-serializing data.
Home-page: https://gitlab.com/vmware/idem/pop-serial
Author: VMware, Inc.
Author-email: idemproject@vmware.com
License: Apache Software License 2.0
Project-URL: Code, https://gitlab.com/vmware/idem/pop-serial
Project-URL: Issue tracker, https://gitlab.com/vmware/idem/pop-serial/issues
Platform: UNKNOWN
Classifier: Environment :: Console
Classifier: Intended Audience :: Developers
Classifier: Intended Audience :: Information Technology
Classifier: Intended Audience :: System Administrators
Classifier: Operating System :: OS Independent
Classifier: Programming Language :: Python
Classifier: Programming Language :: Python :: 3.8
Classifier: Programming Language :: Python :: 3.9
Classifier: Programming Language :: Python :: 3.10
Classifier: Programming Language :: Python :: 3.11
Classifier: Development Status :: 5 - Production/Stable
Classifier: License :: OSI Approved :: Apache Software License
Requires-Python: >=3.8
License-File: LICENSE
Requires-Dist: pop
Requires-Dist: msgpack
